interfacekit/__init__.py
interfacekit/cli.py
interfacekit/version.py
interfacekit-0.0.1.dist-info/METADATA
interfacekit-0.0.1.dist-info/WHEEL
interfacekit-0.0.1.dist-info/entry_points.txt
interfacekit-0.0.1.dist-info/top_level.txt
interfacekit-0.0.1.dist-info/RECORD
