Metadata-Version: 2.1
Name: interfacekit
Version: 0.0.1
Summary: 🤫
Home-page: https://interfacekit.ai
Author: NatML Inc
Author-email: hi@interfacekit.ai
License: Apache License 2.0
Project-URL: Documentation, https://docs.interfacekit.ai/python
Project-URL: Source, https://github.com/interface-kit/InterfaceKit-Py
Platform: UNKNOWN
Classifier: Programming Language :: Python :: 3
Classifier: License :: OSI Approved :: Apache Software License
Classifier: Operating System :: OS Independent
Classifier: Topic :: Scientific/Engineering :: Image Recognition
Classifier: Topic :: Software Development :: Libraries
Requires-Python: >=3.6
Requires-Dist: numpy
Requires-Dist: Pillow
